python_test_aviz/__init__.py
python_test_aviz/aviz_test.py
python_test_aviz/custom_python_logger_test.py
python_test_aviz/notion_test.py
python_test_aviz/python_jira_plus_test.py
python_test_aviz/python_pandas_translation_test.py
python_test_aviz/python_simple_email_sender_test.py
python_test_aviz/tests/__init__.py
python_test_aviz/tests/conftest.py
python_test_aviz/tests/test_dummy.py
python_test_aviz-1.0.10.dist-info/licenses/LICENSE
python_test_aviz-1.0.10.dist-info/METADATA
python_test_aviz-1.0.10.dist-info/WHEEL
python_test_aviz-1.0.10.dist-info/top_level.txt
python_test_aviz-1.0.10.dist-info/RECORD
