Metadata-Version: 2.4
Name: python-test-aviz
Version: 1.0.10
Summary: A test repository for testing the publishing process of a Python package.
Home-page: https://github.com/aviz92/python-test-aviz
Author: Avi Zaguri
Author-email: 
Project-URL: Repository, https://github.com/aviz92/python-test-aviz
Requires-Python: >=3.11
License-File: LICENSE
Requires-Dist: setuptools
Requires-Dist: wheel
Requires-Dist: dotenv
Requires-Dist: twine
Requires-Dist: pytest
Requires-Dist: pandas
Requires-Dist: pytest-mypy
Requires-Dist: custom-python-logger
Requires-Dist: python-jira-plus
Requires-Dist: python-notion-plus
Requires-Dist: python-pandas-translation
Requires-Dist: python-simple-email-sender
Dynamic: author
Dynamic: description
Dynamic: description-content-type
Dynamic: home-page
Dynamic: license-file
Dynamic: project-url
Dynamic: requires-dist
Dynamic: requires-python
Dynamic: summary
